{
  "airdrops": [
    {
      "token": "TITN",
      "name": "THORWallet",
      "date": "2025-11-03",
      "time": "16:00",
      "points": 240,
      "phase": 1,
      "language": "en",
      "status": "announced",
      "utc": "",
      "futures_listed": false,
      "amount": "320",
      "type": "",
      "created_timestamp": 1761978927,
      "updated_timestamp": 1762150509,
      "system_timestamp": 1762150509,
      "completed": true,
      "has_homonym": false,
      "spot_listed": false,
      "contract_address": "0xe62bfbe57763ec24c0f130426f34dbce11fc5b06",
      "chain_id": "8453"
    },
    {
      "token": "KITE",
      "name": "Kite",
      "date": "2025-11-03",
      "time": "19:00",
      "points": "237",
      "phase": 1,
      "language": "en",
      "status": "announced",
      "utc": "",
      "futures_listed": true,
      "amount": "500",
      "type": "claim",
      "created_timestamp": 1761831447,
      "updated_timestamp": 1762159409,
      "system_timestamp": 1762159409,
      "completed": false,
      "has_homonym": false,
      "spot_listed": true,
      "contract_address": "0x904567252d8f48555b7447c67dca23f0372e16be",
      "chain_id": "56"
    },
    {
      "token": "KITE",
      "name": "Kite",
      "date": "2025-11-03",
      "time": "19:00",
      "points": 215,
      "amount": "500",
      "type": "grab",
      "phase": 2,
      "language": "en",
      "status": "announced",
      "futures_listed": true,
      "created_timestamp": 1762156845,
      "updated_timestamp": 1762159409,
      "system_timestamp": 1762159409,
      "contract_address": "0x904567252d8f48555b7447c67dca23f0372e16be",
      "chain_id": "56",
      "completed": true,
      "has_homonym": false,
      "spot_listed": true
    },
    {
      "token": "TYCOON",
      "name": "Dino Tycoon",
      "date": "2025-11-04",
      "time": "15:00",
      "points": "230",
      "phase": 1,
      "language": "zh",
      "status": "announced",
      "utc": "",
      "futures_listed": false,
      "amount": "375",
      "type": "grab",
      "created_timestamp": 1762063865,
      "updated_timestamp": 1762238064,
      "system_timestamp": 1762238064,
      "completed": false,
      "has_homonym": false,
      "spot_listed": false,
      "contract_address": "0x915c882e4f67D5FED79889353BFdB0ad213E9b97",
      "chain_id": "56"
    },
    {
      "token": "TRUST",
      "name": "Intuition",
      "date": "2025-11-05",
      "time": "17:00",
      "phase": 1,
      "language": "zh",
      "status": "announced",
      "futures_listed": true,
      "system_timestamp": 1762178118,
      "created_timestamp": 1762150323,
      "updated_timestamp": 1762178118,
      "points": "",
      "amount": "",
      "type": "",
      "contract_address": "0x6cd905dF2Ed214b22e0d48FF17CD4200C1C6d8A3",
      "chain_id": "8453"
    }
  ]
}